setup.py
sendotp/__init__.py
sendotp/sendotp.py
sendotp.egg-info/PKG-INFO
sendotp.egg-info/SOURCES.txt
sendotp.egg-info/dependency_links.txt
sendotp.egg-info/not-zip-safe
sendotp.egg-info/top_level.txt