Metadata-Version: 1.0
Name: sendotp
Version: 0.0.3
Summary: For sending OTP via MSG91
Home-page: https://github.com/MSG91/sendotp-python
Author: Rahul Chordiya
Author-email: rahul@walkover.in
License: MIT
Platform: UNKNOWN
